[{"id": 57, "fullName": "Arsenal FC", "shortName": "Arsenal", "TLA": "ARS"}, {"id": 58, "fullName": "Aston Villa FC", "shortName": "Aston Villa", "TLA": "AVL"}, {"id": 61, "fullName": "Chelsea FC", "shortName": "Chelsea", "TLA": "CHE"}, {"id": 62, "fullName": "Everton FC", "shortName": "Everton", "TLA": "EVE"}, {"id": 63, "fullName": "Fulham FC", "shortName": "Fulham", "TLA": "FUL"}, {"id": 64, "fullName": "Liverpool FC", "shortName": "Liverpool", "TLA": "LIV"}, {"id": 65, "fullName": "Manchester City FC", "shortName": "Man City", "TLA": "MCI"}, {"id": 66, "fullName": "Manchester United FC", "shortName": "Man United", "TLA": "MUN"}, {"id": 67, "fullName": "Newcastle United FC", "shortName": "Newcastle", "TLA": "NEW"}, {"id": 73, "fullName": "Tottenham Hotspur FC", "shortName": "Tottenham", "TLA": "TOT"}, {"id": 76, "fullName": "Wolverhampton Wanderers FC", "shortName": "Wolverhampton", "TLA": "WOL"}, {"id": 328, "fullName": "Burnley FC", "shortName": "Burnley", "TLA": "BUR"}, {"id": 351, "fullName": "Nottingham Forest FC", "shortName": "Nottingham", "TLA": "NOT"}, {"id": 354, "fullName": "Crystal Palace FC", "shortName": "Crystal Palace", "TLA": "CRY"}, {"id": 356, "fullName": "Sheffield United FC", "shortName": "Sheffield Utd", "TLA": "SHE"}, {"id": 389, "fullName": "Luton Town FC", "shortName": "Luton Town", "TLA": "LUT"}, {"id": 397, "fullName": "Brighton & Hove Albion FC", "shortName": "Brighton Hove", "TLA": "BHA"}, {"id": 402, "fullName": "Brentford FC", "shortName": "Brentford", "TLA": "BRE"}, {"id": 563, "fullName": "West Ham United FC", "shortName": "West Ham", "TLA": "WHU"}, {"id": 1044, "fullName": "AFC Bournemouth", "shortName": "Bournemouth", "TLA": "BOU"}, {"id": 77, "fullName": "Athletic Club", "shortName": "Athletic", "TLA": "ATH"}, {"id": 78, "fullName": "Club Atl\u00e9tico de Madrid", "shortName": "Atleti", "TLA": "ATL"}, {"id": 79, "fullName": "CA Osasuna", "shortName": "Osasuna", "TLA": "OSA"}, {"id": 81, "fullName": "FC Barcelona", "shortName": "Bar\u00e7a", "TLA": "FCB"}, {"id": 82, "fullName": "Getafe CF", "shortName": "Getafe", "TLA": "GET"}, {"id": 83, "fullName": "Granada CF", "shortName": "Granada", "TLA": "GRA"}, {"id": 86, "fullName": "Real Madrid CF", "shortName": "Real Madrid", "TLA": "RMA"}, {"id": 87, "fullName": "Rayo Vallecano de Madrid", "shortName": "Rayo Vallecano", "TLA": "RAY"}, {"id": 89, "fullName": "RCD Mallorca", "shortName": "Mallorca", "TLA": "MAL"}, {"id": 90, "fullName": "Real Betis Balompi\u00e9", "shortName": "Real Betis", "TLA": "BET"}, {"id": 92, "fullName": "Real Sociedad de F\u00fatbol", "shortName": "Real Sociedad", "TLA": "RSO"}, {"id": 94, "fullName": "Villarreal CF", "shortName": "Villarreal", "TLA": "VIL"}, {"id": 95, "fullName": "Valencia CF", "shortName": "Valencia", "TLA": "VAL"}, {"id": 263, "fullName": "Deportivo Alav\u00e9s", "shortName": "Alav\u00e9s", "TLA": "ALA"}, {"id": 264, "fullName": "C\u00e1diz CF", "shortName": "C\u00e1diz CF", "TLA": "CAD"}, {"id": 267, "fullName": "UD Almer\u00eda", "shortName": "Almer\u00eda", "TLA": "ALM"}, {"id": 275, "fullName": "UD Las Palmas", "shortName": "Las Palmas", "TLA": "LPA"}, {"id": 298, "fullName": "Girona FC", "shortName": "Girona", "TLA": "GIR"}, {"id": 558, "fullName": "RC Celta de Vigo", "shortName": "Celta", "TLA": "CEL"}, {"id": 559, "fullName": "Sevilla FC", "shortName": "Sevilla FC", "TLA": "SEV"}, {"id": 511, "fullName": "Toulouse FC", "shortName": "Toulouse", "TLA": "TOU"}, {"id": 512, "fullName": "Stade Brestois 29", "shortName": "Brest", "TLA": "BRE"}, {"id": 516, "fullName": "Olympique de Marseille", "shortName": "Marseille", "TLA": "MAR"}, {"id": 518, "fullName": "Montpellier HSC", "shortName": "Montpellier", "TLA": "MON"}, {"id": 521, "fullName": "Lille OSC", "shortName": "Lille", "TLA": "LIL"}, {"id": 522, "fullName": "OGC Nice", "shortName": "Nice", "TLA": "NIC"}, {"id": 523, "fullName": "Olympique Lyonnais", "shortName": "Olympique Lyon", "TLA": "LYO"}, {"id": 524, "fullName": "Paris Saint-Germain FC", "shortName": "PSG", "TLA": "PSG"}, {"id": 525, "fullName": "FC Lorient", "shortName": "Lorient", "TLA": "FCL"}, {"id": 529, "fullName": "Stade Rennais FC 1901", "shortName": "Stade Rennais", "TLA": "REN"}, {"id": 533, "fullName": "Le Havre AC", "shortName": "Le Havre", "TLA": "HAC"}, {"id": 541, "fullName": "Clermont Foot 63", "shortName": "Clermont Foot", "TLA": "CLF"}, {"id": 543, "fullName": "FC Nantes", "shortName": "Nantes", "TLA": "NAN"}, {"id": 545, "fullName": "FC Metz", "shortName": "FC Metz", "TLA": "FCM"}, {"id": 546, "fullName": "Racing Club de Lens", "shortName": "RC Lens", "TLA": "RCL"}, {"id": 547, "fullName": "Stade de Reims", "shortName": "Stade de Reims", "TLA": "SDR"}, {"id": 548, "fullName": "AS Monaco FC", "shortName": "Monaco", "TLA": "ASM"}, {"id": 576, "fullName": "RC Strasbourg Alsace", "shortName": "Strasbourg", "TLA": "RC "}, {"id": 1, "fullName": "1. FC K\u00f6ln", "shortName": "1. FC K\u00f6ln", "TLA": "KOE"}, {"id": 2, "fullName": "TSG 1899 Hoffenheim", "shortName": "Hoffenheim", "TLA": "TSG"}, {"id": 3, "fullName": "Bayer 04 Leverkusen", "shortName": "Leverkusen", "TLA": "B04"}, {"id": 4, "fullName": "Borussia Dortmund", "shortName": "Dortmund", "TLA": "BVB"}, {"id": 5, "fullName": "FC Bayern M\u00fcnchen", "shortName": "Bayern", "TLA": "FCB"}, {"id": 10, "fullName": "VfB Stuttgart", "shortName": "Stuttgart", "TLA": "VFB"}, {"id": 11, "fullName": "VfL Wolfsburg", "shortName": "Wolfsburg", "TLA": "WOB"}, {"id": 12, "fullName": "SV Werder Bremen", "shortName": "Bremen", "TLA": "SVW"}, {"id": 15, "fullName": "1. FSV Mainz 05", "shortName": "Mainz", "TLA": "M05"}, {"id": 16, "fullName": "FC Augsburg", "shortName": "Augsburg", "TLA": "FCA"}, {"id": 17, "fullName": "SC Freiburg", "shortName": "Freiburg", "TLA": "SCF"}, {"id": 18, "fullName": "Borussia M\u00f6nchengladbach", "shortName": "M'gladbach", "TLA": "BMG"}, {"id": 19, "fullName": "Eintracht Frankfurt", "shortName": "Frankfurt", "TLA": "SGE"}, {"id": 28, "fullName": "1. FC Union Berlin", "shortName": "Union Berlin", "TLA": "UNB"}, {"id": 36, "fullName": "VfL Bochum 1848", "shortName": "Bochum", "TLA": "BOC"}, {"id": 44, "fullName": "1. FC Heidenheim 1846", "shortName": "Heidenheim", "TLA": "HEI"}, {"id": 55, "fullName": "SV Darmstadt 98", "shortName": "Darmstadt", "TLA": "SVD"}, {"id": 721, "fullName": "RB Leipzig", "shortName": "RB Leipzig", "TLA": "RBL"}, {"id": 98, "fullName": "AC Milan", "shortName": "Milan", "TLA": "MIL"}, {"id": 99, "fullName": "ACF Fiorentina", "shortName": "Fiorentina", "TLA": "FIO"}, {"id": 100, "fullName": "AS Roma", "shortName": "Roma", "TLA": "ROM"}, {"id": 102, "fullName": "Atalanta BC", "shortName": "Atalanta", "TLA": "ATA"}, {"id": 103, "fullName": "Bologna FC 1909", "shortName": "Bologna", "TLA": "BOL"}, {"id": 104, "fullName": "Cagliari Calcio", "shortName": "Cagliari", "TLA": "CAG"}, {"id": 107, "fullName": "Genoa CFC", "shortName": "Genoa", "TLA": "GEN"}, {"id": 108, "fullName": "FC Internazionale Milano", "shortName": "Inter", "TLA": "INT"}, {"id": 109, "fullName": "Juventus FC", "shortName": "Juventus", "TLA": "JUV"}, {"id": 110, "fullName": "SS Lazio", "shortName": "Lazio", "TLA": "LAZ"}, {"id": 113, "fullName": "SSC Napoli", "shortName": "Napoli", "TLA": "NAP"}, {"id": 115, "fullName": "Udinese Calcio", "shortName": "Udinese", "TLA": "UDI"}, {"id": 445, "fullName": "Empoli FC", "shortName": "Empoli", "TLA": "EMP"}, {"id": 450, "fullName": "Hellas Verona FC", "shortName": "Verona", "TLA": "HVE"}, {"id": 455, "fullName": "US Salernitana 1919", "shortName": "Salernitana", "TLA": "SAL"}, {"id": 470, "fullName": "Frosinone Calcio", "shortName": "Frosinone", "TLA": "FRO"}, {"id": 471, "fullName": "US Sassuolo Calcio", "shortName": "Sassuolo", "TLA": "SAS"}, {"id": 586, "fullName": "Torino FC", "shortName": "Torino", "TLA": "TOR"}, {"id": 5890, "fullName": "US Lecce", "shortName": "Lecce", "TLA": "USL"}, {"id": 5911, "fullName": "AC Monza", "shortName": "Monza", "TLA": "MON"}, {"id": 4, "fullName": "Borussia Dortmund", "shortName": "Dortmund", "TLA": "BVB"}, {"id": 5, "fullName": "FC Bayern M\u00fcnchen", "shortName": "Bayern", "TLA": "FCB"}, {"id": 28, "fullName": "1. FC Union Berlin", "shortName": "Union Berlin", "TLA": "UNB"}, {"id": 57, "fullName": "Arsenal FC", "shortName": "Arsenal", "TLA": "ARS"}, {"id": 65, "fullName": "Manchester City FC", "shortName": "Man City", "TLA": "MCI"}, {"id": 66, "fullName": "Manchester United FC", "shortName": "Man United", "TLA": "MUN"}, {"id": 67, "fullName": "Newcastle United FC", "shortName": "Newcastle", "TLA": "NEW"}, {"id": 78, "fullName": "Club Atl\u00e9tico de Madrid", "shortName": "Atleti", "TLA": "ATL"}, {"id": 81, "fullName": "FC Barcelona", "shortName": "Bar\u00e7a", "TLA": "FCB"}, {"id": 86, "fullName": "Real Madrid CF", "shortName": "Real Madrid", "TLA": "RMA"}, {"id": 92, "fullName": "Real Sociedad de F\u00fatbol", "shortName": "Real Sociedad", "TLA": "RSO"}, {"id": 98, "fullName": "AC Milan", "shortName": "Milan", "TLA": "MIL"}, {"id": 108, "fullName": "FC Internazionale Milano", "shortName": "Inter", "TLA": "INT"}, {"id": 110, "fullName": "SS Lazio", "shortName": "Lazio", "TLA": "LAZ"}, {"id": 113, "fullName": "SSC Napoli", "shortName": "Napoli", "TLA": "NAP"}, {"id": 503, "fullName": "FC Porto", "shortName": "Porto", "TLA": "FCP"}, {"id": 524, "fullName": "Paris Saint-Germain FC", "shortName": "PSG", "TLA": "PSG"}, {"id": 546, "fullName": "Racing Club de Lens", "shortName": "RC Lens", "TLA": "RCL"}, {"id": 559, "fullName": "Sevilla FC", "shortName": "Sevilla FC", "TLA": "SEV"}, {"id": 610, "fullName": "Galatasaray SK", "shortName": "Galatasaray", "TLA": "GAL"}, {"id": 674, "fullName": "PSV", "shortName": "PSV", "TLA": "PSV"}, {"id": 675, "fullName": "Feyenoord Rotterdam", "shortName": "Feyenoord", "TLA": "FEY"}, {"id": 721, "fullName": "RB Leipzig", "shortName": "RB Leipzig", "TLA": "RBL"}, {"id": 732, "fullName": "Celtic FC", "shortName": "Celtic", "TLA": "CEL"}, {"id": 1864, "fullName": "Royal Antwerp FC", "shortName": "Antwerp FC", "TLA": "ANT"}, {"id": 1871, "fullName": "BSC Young Boys", "shortName": "Young Boys", "TLA": "YOB"}, {"id": 1876, "fullName": "FC K\u00f8benhavn", "shortName": "K\u00f8benhavn", "TLA": "KOB"}, {"id": 1877, "fullName": "FC Red Bull Salzburg", "shortName": "RB Salzburg", "TLA": "RBS"}, {"id": 1887, "fullName": "FK Shakhtar Donetsk", "shortName": "Shaktar", "TLA": "SHD"}, {"id": 1903, "fullName": "Sport Lisboa e Benfica", "shortName": "SL Benfica", "TLA": "BEN"}, {"id": 5613, "fullName": "Sporting Clube de Braga", "shortName": "Braga", "TLA": "SCB"}, {"id": 7283, "fullName": "FK Crvena Zvezda", "shortName": "Crvena Zvedza", "TLA": "CRV"}]